audiotsm/__init__.py
audiotsm/ola.py
audiotsm/phasevocoder.py
audiotsm/wsola.py
audiotsm/base/__init__.py
audiotsm/base/analysis_synthesis.py
audiotsm/base/tsm.py
audiotsm/gstreamer/__init__.py
audiotsm/gstreamer/base.py
audiotsm/gstreamer/ola.py
audiotsm/gstreamer/phasevocoder.py
audiotsm/gstreamer/wsola.py
audiotsm/io/__init__.py
audiotsm/io/array.py
audiotsm/io/base.py
audiotsm/io/stream.py
audiotsm/io/wav.py
audiotsm/utils/__init__.py
audiotsm/utils/cbuffer.py
audiotsm/utils/normalizebuffer.py
audiotsm/utils/windows.py
audiotsm-0.1.2.dist-info/DESCRIPTION.rst
audiotsm-0.1.2.dist-info/LICENSE.txt
audiotsm-0.1.2.dist-info/METADATA
audiotsm-0.1.2.dist-info/RECORD
audiotsm-0.1.2.dist-info/WHEEL
audiotsm-0.1.2.dist-info/metadata.json
audiotsm-0.1.2.dist-info/top_level.txt
