Metadata-Version: 1.1
Name: audiotsm
Version: 0.1.2
Summary: A real-time audio time-scale modification library
Home-page: https://github.com/Muges/audiotsm
Author: Muges
Author-email: git@muges.fr
License: MIT
Platform: UNKNOWN
Classifier: License :: OSI Approved :: MIT License
Classifier: Programming Language :: Python
Classifier: Programming Language :: Python :: 2
Classifier: Programming Language :: Python :: 2.7
Classifier: Programming Language :: Python :: 3
Classifier: Programming Language :: Python :: 3.4
Classifier: Programming Language :: Python :: 3.5
Classifier: Programming Language :: Python :: 3.6
Classifier: Topic :: Multimedia :: Sound/Audio
